CHANGELOG.md
CONTRIBUTORS.md
LICENSE
MANIFEST.in
README.md
setup.cfg
setup.py
mdat/__init__.py
mdat/__main__.py
mdat/core.py
mdat.egg-info/PKG-INFO
mdat.egg-info/SOURCES.txt
mdat.egg-info/dependency_links.txt
mdat.egg-info/entry_points.txt
mdat.egg-info/requires.txt
mdat.egg-info/top_level.txt
tests/__init__.py
tests/test_bestAlternative.py
tests/test_choquetIntegral.py
tests/test_fuzzyMeasure.py