Metadata-Version: 1.0
Name: mdat
Version: 0.3.1.2
Summary: A decision aid designed to select the best of two or more alternatives given responses to a list of criteria
Home-page: https://github.com/ctsit/mdat
Author: pbc
Author-email: ctsit@ctsi.ufl.edu
License: Apache 2.0
Platform: UNKNOWN
